sphinxcontrib_phpdomain-0.13.2-py3.13-nspkg.pth
sphinxcontrib/phpdomain.py
sphinxcontrib_phpdomain-0.13.2.dist-info/licenses/LICENSE
sphinxcontrib_phpdomain-0.13.2.dist-info/METADATA
sphinxcontrib_phpdomain-0.13.2.dist-info/WHEEL
sphinxcontrib_phpdomain-0.13.2.dist-info/namespace_packages.txt
sphinxcontrib_phpdomain-0.13.2.dist-info/top_level.txt
sphinxcontrib_phpdomain-0.13.2.dist-info/RECORD
