Metadata-Version: 2.4
Name: sphinxcontrib-phpdomain
Version: 0.13.2
Summary: Sphinx extension to enable documenting PHP code
Home-page: https://github.com/markstory/sphinxcontrib-phpdomain
Download-URL: http://pypi.python.org/pypi/sphinxcontrib-phpdomain
Author: Mark Story
Author-email: mark@mark-story.com
License: BSD
Project-URL: Documentation, https://markstory.github.io/sphinxcontrib-phpdomain/
Platform: any
Classifier: Environment :: Console
Classifier: Environment :: Web Environment
Classifier: Framework :: Sphinx :: Domain
Classifier: Intended Audience :: Developers
Classifier: License :: OSI Approved :: BSD License
Classifier: Operating System :: OS Independent
Classifier: Programming Language :: Python
Classifier: Topic :: Documentation
Classifier: Topic :: Utilities
License-File: LICENSE
Requires-Dist: sphinx<9.0,>=1.3
Dynamic: author
Dynamic: author-email
Dynamic: classifier
Dynamic: description
Dynamic: download-url
Dynamic: home-page
Dynamic: license
Dynamic: license-file
Dynamic: platform
Dynamic: project-url
Dynamic: requires-dist
Dynamic: summary
